aws_fuzzy_finder/__init__.py
aws_fuzzy_finder/aws_utils.py
aws_fuzzy_finder/main.py
aws_fuzzy_finder/settings.py
aws_fuzzy_finder/libs/fzf-0.17.0-darwin_386
aws_fuzzy_finder/libs/fzf-0.17.0-darwin_amd64
aws_fuzzy_finder/libs/fzf-0.17.0-linux_386
aws_fuzzy_finder/libs/fzf-0.17.0-linux_amd64
aws_fuzzy_finder-1.1.1.dist-info/LICENSE
aws_fuzzy_finder-1.1.1.dist-info/METADATA
aws_fuzzy_finder-1.1.1.dist-info/WHEEL
aws_fuzzy_finder-1.1.1.dist-info/entry_points.txt
aws_fuzzy_finder-1.1.1.dist-info/top_level.txt
aws_fuzzy_finder-1.1.1.dist-info/RECORD
