Metadata-Version: 2.1
Name: aws-fuzzy-finder
Version: 1.1.1
Summary: SSH into AWS instances using fuzzy search through tags.
Home-page: https://github.com/pmazurek/aws-fuzzy-finder
Author: Piotr Mazurek, Daria Rudkiewicz
Author-email: UNKNOWN
License: UNKNOWN
Download-URL: https://github.com/pmazurek/aws-fuzzy-finder/tarball/v1.1.1
Keywords: aws,ssh,fuzzy,ec2
Platform: UNKNOWN
Requires-Dist: boto3 (>=1.3.1)
Requires-Dist: click (>=6.6)
